dlogg_driver/__init__.py
dlogg_driver/definitions.py
dlogg_driver/device.py
dlogg_driver-0.2.1.dist-info/DESCRIPTION.rst
dlogg_driver-0.2.1.dist-info/METADATA
dlogg_driver-0.2.1.dist-info/RECORD
dlogg_driver-0.2.1.dist-info/WHEEL
dlogg_driver-0.2.1.dist-info/metadata.json
dlogg_driver-0.2.1.dist-info/top_level.txt
