Metadata-Version: 2.0
Name: dlogg-driver
Version: 0.2.1
Summary: Unofficial library to read data from a Technische Alternative D-LOGG device.
Home-page: https://github.com/ubruhin/python-dlogg-driver
Author: U. Bruhin
Author-email: python-dlogg@ubruhin.ch
License: GPLv3
Keywords: technische alternative,dlogg,d-logg,d logg
Platform: UNKNOWN
Classifier: Development Status :: 3 - Alpha
Classifier: Intended Audience :: Developers
Classifier: License :: OSI Approved :: GNU Lesser General Public License v3 or later (LGPLv3+)
Classifier: Programming Language :: Python :: 2.7
Requires-Dist: enum34
Requires-Dist: pyserial
